setup.cfg
setup.py
django_ajax_resp/__init__.py
django_ajax_resp/django_ajax_resp.py
django_ajax_resp.egg-info/PKG-INFO
django_ajax_resp.egg-info/SOURCES.txt
django_ajax_resp.egg-info/dependency_links.txt
django_ajax_resp.egg-info/top_level.txt