Metadata-Version: 1.1
Name: django-ajax-resp
Version: 0.0.1-dev
Summary: A lightweight ajax framework for Django.
Home-page: https://github.com/matteofattore-nextage/django-ajax-resp
Author: Matteo Fattore
Author-email: matteo.fattore@nextage-on.com
License: Apache 2
Download-URL: https://github.com/matteofattore-nextage/django-ajax-resp/zipball/master
Platform: UNKNOWN
Classifier: Development Status :: 3 - Alpha
Classifier: Environment :: Web Environment
Classifier: Framework :: Django
Classifier: Intended Audience :: Developers
Classifier: Operating System :: OS Independent
Classifier: Programming Language :: Python
Classifier: Topic :: Internet :: WWW/HTTP
